{
  "title": "励志打遍天下无敌手——我是指街霸6",
  "description": "热血励志 × 日常喜剧 × 竞技成长。一个普通宅男在街霸6里从被虐菜鸡蜕变为找到自我风格的故事——关于游戏，关于孤独探索，关于为什么而战。",
  "segments": [
    {
      "id": "s1",
      "text": "游戏厅里，五彩斑斓的灯光映照着每一台游戏机，人群熙攘，欢呼声此起彼伏。林羽站在一台街霸6的游戏机前，双眼闪烁着期待的光芒。他深吸一口气，按下了开始键。屏幕上的角色栩栩如生，但对手的操作却如同闪电般迅速，几个回合下来，林羽已经摇摇欲坠。",
      "effect": "typewriter",
      "speed": 55,
      "background": {
        "image": "assets/bg_arcade_evening.png"
      },
      "character_image": "assets/char_林羽_calm.png"
    },
    {
      "id": "s2",
      "text": "\"哎呀，这家伙真菜！\"旁边一个戴着帽子的青年忍不住笑出声来。",
      "effect": "typewriter",
      "speed": 55,
      "character_image": "assets/char_林羽_calm.png"
    },
    {
      "id": "s3",
      "text": "林羽咬紧牙关，努力不去理会周围的嘲笑声。他的双手微微颤抖，心里充满了挫败感。\"我是不是真的不适合玩这个？\"他在心里问自己。",
      "effect": "shake",
      "speed": 15,
      "character_image": "assets/char_林羽_frustrated.png"
    },
    {
      "id": "s4",
      "text": "就在这时，苏瑶走了过来，拍了拍林羽的肩膀。\"别灰心，刚开始都是这样的。\"她的声音温暖而有力，仿佛一缕阳光照进了林羽的心房。",
      "effect": "typewriter",
      "speed": 55,
      "character_image": "assets/char_苏瑶_friendly.png"
    },
    {
      "id": "s5",
      "text": "林羽抬起头，看到苏瑶鼓励的眼神，心中涌起一丝暖意。\"可是……我真的很弱。\"他低声说道。",
      "effect": "typewriter",
      "speed": 55,
      "character_image": "assets/char_苏瑶_friendly.png"
    },
    {
      "id": "s6",
      "text": "苏瑶笑了笑，\"每个人都有成长的过程，重要的是不放弃。\"",
      "effect": "typewriter",
      "speed": 55,
      "character_image": "assets/char_苏瑶_friendly.png"
    },
    {
      "id": "s7",
      "text": "李昊在一旁听到了他们的对话，忍不住插嘴道：\"不放弃？说得容易做起来难。你看看你这操作，简直就是菜鸟中的菜鸟。\"",
      "effect": "typewriter",
      "speed": 55,
      "character_image": "assets/char_李昊_confident.png"
    },
    {
      "id": "s8",
      "text": "林羽的脸颊微微发烫，他低下头，心里充满了不甘。苏瑶看了李昊一眼，淡淡地说道：\"每个人都有自己的节奏，不是吗？\"",
      "effect": "typewriter",
      "speed": 55,
      "character_image": "assets/char_苏瑶_friendly.png"
    },
    {
      "id": "s9",
      "text": "李昊冷哼一声，转身离去。林羽看着他的背影，心中暗暗发誓，总有一天，他要证明自己。",
      "effect": "typewriter",
      "speed": 55,
      "character_image": "assets/char_李昊_confident.png"
    },
    {
      "id": "s10",
      "text": "游戏厅的喧嚣渐渐远去，林羽站在空荡荡的街道上，心中五味杂陈。霓虹灯的倒影在积水的地砖上拉成长条，晃晃悠悠。他抬头看了看夜空——天色已深，却没有星星，城市的光污染把它们都挤走了。他把手插进口袋，指尖触到了今天用完的游戏币，冰凉的。",
      "effect": "typewriter",
      "speed": 55,
      "background": {
        "image": "assets/bg_street_night.png"
      },
      "character_image": "assets/char_林羽_calm.png"
    },
    {
      "id": "s11",
      "text": "\"我不能就这样放弃。\"他在心里默念道。",
      "effect": "typewriter",
      "speed": 55,
      "character_image": "assets/char_林羽_calm.png"
    },
    {
      "id": "s12",
      "text": "回到家后，林羽坐在电脑前，打开街霸6的练习模式。屋子里只有风扇嗡嗡作响，偶尔窗外传来几声摩托车声。他关掉了背景音乐，只盯着屏幕上那个静止待命的角色，像是在打量一个陌生的武器。",
      "effect": "typewriter",
      "speed": 55,
      "background": {
        "effects": [
          "fade"
        ],
        "image": "assets/bg_room_night.png"
      },
      "character_image": "assets/char_林羽_calm.png"
    },
    {
      "id": "s13",
      "text": "他的手指在手柄上反复搓了搓，按下了开始。屏幕上的角色做出了一个笨拙的升龙拳，然后跌回来。林羽皱了皱眉，又按了一次。还是那个奇怪的倒三角拳，越练越僵。",
      "effect": "typewriter",
      "speed": 55,
      "background": {
        "image": "assets/bg_room_night.png"
      },
      "character_image": "assets/char_林羽_calm.png"
    },
    {
      "id": "s14",
      "text": "深夜十二点，月光透过百叶窗的缝隙在桌面上切出细条。林羽的手指已经微微发酸，他活动了一下关节，听见指节\"咔\"的一声，暗想今天就到这里算了——然后又在椅子上多坐了二十分钟。",
      "effect": "typewriter",
      "speed": 55,
      "background": {
        "effects": [
          "fade"
        ],
        "image": "assets/bg_room_night.png"
      },
      "character_image": "assets/char_林羽_calm.png"
    },
    {
      "id": "s15",
      "text": "他在B站翻到了一个街霸6的基础教学视频，手机架在旁边，跟着视频一帧一帧地模仿指法。他用食指在桌面上轻轻划着方向：下→斜下→前，下→斜下→前。月光把他的手影映在桌布上，像一只迷路的鸟来回踱步。",
      "effect": "typewriter",
      "speed": 55,
      "background": {
        "image": "assets/bg_room_night.png"
      },
      "character_image": "assets/char_林羽_calm.png"
    },
    {
      "id": "s16",
      "text": "这种孤独并不难受，林羽想，有点像小时候一个人背乘法表。",
      "effect": "typewriter",
      "speed": 55,
      "character_image": "assets/char_林羽_calm.png"
    },
    {
      "id": "s17",
      "text": "练习第三天，林羽刷到了一个帖子：一个没有右手的玩家用脚踩手柄，段位打到了钻石。林羽盯着那张截图看了很久，喉咙有点哽。",
      "effect": "typewriter",
      "speed": 55,
      "character_image": "assets/char_林羽_calm.png"
    },
    {
      "id": "s18",
      "text": "他把自己的失误录像重新调出来，这次不是看着难受，而是真的开始分析——哪一帧漏掉了输入，哪一次乱跳给对手送了连招。他用便利贴在显示器旁边写下两行字，用马克笔尽量写得大一些：看清楚再出手。忍。",
      "effect": "typewriter",
      "speed": 55,
      "background": {
        "image": "assets/bg_room_night.png"
      },
      "character_image": "assets/char_林羽_calm.png"
    },
    {
      "id": "s19",
      "text": "一周后，林羽在网络排位赛里第一次赢了一局线上的陌生人。对方段位是白银，赢得并不好看，是对方失误后他抓了一个反击。",
      "effect": "shake",
      "speed": 15,
      "background": {
        "effects": [
          "fade"
        ],
        "image": "assets/bg_room_night.png"
      },
      "character_image": "assets/char_林羽_winning.png"
    },
    {
      "id": "s20",
      "text": "他坐在椅子上，盯着屏幕上\"胜利\"二字，大概有十秒钟没动。然后他笑了——不是那种欢呼雀跃的笑，只是嘴角自己往上翘，他都没发现。",
      "effect": "typewriter",
      "speed": 55,
      "character_image": "assets/char_林羽_winning.png"
    },
    {
      "id": "s21",
      "text": "周末，林羽再次来到游戏厅。今天的人比平时少一些，靠里的几台街霸6机器空着两台。他把外套搭在椅背上，插币，选角色——还是那个熟悉的女角色，他觉得她出招的节奏更符合自己的习惯。",
      "effect": "typewriter",
      "speed": 55,
      "background": {
        "effects": [
          "fade"
        ],
        "image": "assets/bg_room_night.png"
      },
      "character_image": "assets/char_林羽_calm.png"
    },
    {
      "id": "s22",
      "text": "对面坐下来一个看起来和他差不多年纪的男生，T恤上印着一只宝可梦，发型有点乱，神情漫不经心。林羽在心里估摸了一下：这人也是普通玩家，应该不会太难打。",
      "effect": "typewriter",
      "speed": 55,
      "character_image": "assets/char_林羽_calm.png"
    },
    {
      "id": "s23",
      "text": "他手心出了一层薄薄的汗。",
      "effect": "typewriter",
      "speed": 55,
      "character_image": "assets/char_林羽_calm.png"
    },
    {
      "id": "s24",
      "text": "开局，对方直接冲上来按了三下重拳，节奏快但不稳。林羽退了两步守住，手指悄悄划出升龙拳的指令——等一等，不急——然后在对方第三拳落空的瞬间，一拳打了出去。",
      "effect": "typewriter",
      "speed": 55,
      "character_image": "assets/char_林羽_calm.png"
    },
    {
      "id": "s25",
      "text": "\"啊！\"男生叫了一声，后仰靠在椅背上，似乎没料到。",
      "effect": "typewriter",
      "speed": 55,
      "background": {
        "image": "assets/bg_room_night.png"
      },
      "character_image": "assets/char_林羽_calm.png"
    },
    {
      "id": "s26",
      "text": "林羽没有欢呼，只是继续盯着屏幕，心跳却快了半拍。",
      "effect": "typewriter",
      "speed": 55,
      "character_image": "assets/char_林羽_calm.png"
    },
    {
      "id": "s27",
      "text": "第一局，林羽赢了。",
      "effect": "shake",
      "speed": 15,
      "character_image": "assets/char_林羽_winning.png"
    },
    {
      "id": "s28",
      "text": "不夸张，赢得很普通，甚至最后一刀还差点失手——但赢就是赢。他按下继续，又打了第二局。这次对方调整了打法，开始用一个连段压制，林羽跟不上节奏，被打得很狼狈，第二局输了。",
      "effect": "shake",
      "speed": 15,
      "character_image": "assets/char_林羽_frustrated.png"
    },
    {
      "id": "s29",
      "text": "两人打到三局，周围已经聚了两三个人在看。林羽感觉到背后的视线，呼吸刻意放平。",
      "effect": "typewriter",
      "speed": 55,
      "character_image": "assets/char_林羽_calm.png"
    },
    {
      "id": "s30",
      "text": "第三局，林羽把注意力收回到屏幕上。对方在最后一血时开始有些紧张，连击节奏乱了。林羽逮住一个空档，打出了最近练得最熟的那组反击连段——嗖嗖嗖三下，干净利落，倒地。",
      "effect": "shake",
      "speed": 15,
      "character_image": "assets/char_林羽_calm.png"
    },
    {
      "id": "s31",
      "text": "\"好！\"不知道是谁拍了一下机台的侧面。",
      "effect": "typewriter",
      "speed": 55,
      "background": {
        "image": "assets/bg_arcade_evening.png"
      },
      "character_image": "assets/char_林羽_calm.png"
    },
    {
      "id": "s32",
      "text": "林羽站起来，把外套从椅背上拿下来，头发有点乱，耳朵微微发烫。那个宝可梦男生朝他竖了个大拇指，什么也没说，转身去找别的机台了。",
      "effect": "typewriter",
      "speed": 55,
      "background": {
        "image": "assets/bg_room_night.png"
      },
      "character_image": "assets/char_林羽_calm.png"
    },
    {
      "id": "s33",
      "text": "苏瑶不知道什么时候出现在他旁边，语气轻飘飘的：\"看，我说什么来着？\"",
      "effect": "typewriter",
      "speed": 55,
      "character_image": "assets/char_苏瑶_friendly.png"
    },
    {
      "id": "s34",
      "text": "林羽没说话，但嘴角实在没忍住。",
      "effect": "typewriter",
      "speed": 55,
      "character_image": "assets/char_林羽_calm.png"
    },
    {
      "id": "s35",
      "text": "林羽坐在电脑前，心跳加速。他知道，这一刻终于来临了。李昊在网络对战平台上向他发起了挑战。林羽深吸一口气，点击了接受。",
      "effect": "typewriter",
      "speed": 55,
      "background": {
        "effects": [
          "fade"
        ],
        "image": "assets/bg_room_night.png"
      },
      "character_image": "assets/char_李昊_confident.png"
    },
    {
      "id": "s36",
      "text": "屏幕上，两个角色在虚拟的擂台上对峙。林羽的手指在手柄上微微颤抖，他知道，李昊是个强劲的对手。",
      "effect": "typewriter",
      "speed": 55,
      "background": {
        "image": "assets/bg_room_night.png"
      },
      "character_image": "assets/char_李昊_confident.png"
    },
    {
      "id": "s37",
      "text": "第一局开始，林羽的角色被李昊的连招打得措手不及。屏幕上，他的角色一次次被击倒，血量迅速减少。",
      "effect": "shake",
      "speed": 15,
      "character_image": "assets/char_李昊_confident.png"
    },
    {
      "id": "s38",
      "text": "\"不行，我不能这样下去。\"林羽在心里默念道。他努力调整呼吸，集中注意力。那种感觉很熟悉，就像第一天在游戏厅被虐，只是这次他知道了更多，却依然追不上。",
      "effect": "typewriter",
      "speed": 55,
      "background": {
        "image": "assets/bg_arcade_evening.png"
      },
      "character_image": "assets/char_林羽_frustrated.png"
    },
    {
      "id": "s39",
      "text": "然而，第二局依然没有好转。李昊的操作如行云流水，林羽的角色几乎没有还手之力。每一次失败，林羽都能感觉到那种窒息感——不是愤怒，是一种被看穿了底牌的难堪。",
      "effect": "typewriter",
      "speed": 55,
      "character_image": "assets/char_李昊_confident.png"
    },
    {
      "id": "s40",
      "text": "\"我到底哪里做得不对？\"他在心里问自己。屏幕上，加载画面的读条在转，下一局即将开始。",
      "effect": "typewriter",
      "speed": 55,
      "character_image": "assets/char_林羽_calm.png"
    },
    {
      "id": "s41",
      "text": "第三局，林羽决定改变策略。他开始更加注重防守，寻找反击的机会。虽然依然被李昊压制，但他没有放弃。某一刻他甚至抓到了一次机会，打出一个完整的连段——可惜被李昊预判了，一个无敌帧闪过去之后，反手一个过肩摔把他砸在地上。",
      "effect": "shake",
      "speed": 15,
      "character_image": "assets/char_李昊_confident.png"
    },
    {
      "id": "s42",
      "text": "\"再坚持一下，一定会有机会的。\"他在心里鼓励自己。",
      "effect": "typewriter",
      "speed": 55,
      "character_image": "assets/char_林羽_calm.png"
    },
    {
      "id": "s43",
      "text": "第四局，林羽终于找到了一个破绽，成功反击。他的角色打出了一连串连招，李昊的角色被击倒在地。",
      "effect": "shake",
      "speed": 15,
      "character_image": "assets/char_李昊_confident.png"
    },
    {
      "id": "s44",
      "text": "林羽忍不住在椅子上想站起来，手放在桌上。他知道，自己并不是没有机会。",
      "effect": "typewriter",
      "speed": 55,
      "character_image": "assets/char_林羽_calm.png"
    },
    {
      "id": "s45",
      "text": "然而接下来几局，李昊迅速调整，再次占据上风。林羽的角色一次次被击倒，他的心情也随着屏幕上的战况起起伏伏。",
      "effect": "shake",
      "speed": 15,
      "character_image": "assets/char_李昊_confident.png"
    },
    {
      "id": "s46",
      "text": "最后一局，林羽已经拼尽全力。他的手指在手柄上飞快地移动，角色在屏幕上灵活地躲避攻击，寻找反击的机会。但李昊抓住最后一个空档，一场斩杀收了局。",
      "effect": "shake",
      "speed": 15,
      "background": {
        "image": "assets/bg_room_night.png"
      },
      "character_image": "assets/char_李昊_confident.png"
    },
    {
      "id": "s47",
      "text": "屏幕上跳出\"对手获胜\"几个字，那几个字亮了一下就消失了，但它们好像留在了林羽的视网膜上。",
      "effect": "typewriter",
      "speed": 55,
      "character_image": "assets/char_林羽_calm.png"
    },
    {
      "id": "s48",
      "text": "林羽靠在椅背上，闭上眼睛，深深地吸了一口气。",
      "effect": "typewriter",
      "speed": 55,
      "background": {
        "image": "assets/bg_room_night.png"
      },
      "character_image": "assets/char_林羽_calm.png"
    },
    {
      "id": "s49",
      "text": "\"我输了，但我不会放弃。\"他在心里默念道。",
      "effect": "typewriter",
      "speed": 55,
      "character_image": "assets/char_林羽_frustrated.png"
    },
    {
      "id": "s50",
      "text": "就在这时，李昊在对话框里发来消息：\"你那个第四局的反击，有点东西。继续练。\"",
      "effect": "typewriter",
      "speed": 55,
      "character_image": "assets/char_李昊_confident.png"
    },
    {
      "id": "s51",
      "text": "林羽盯着屏幕上的文字看了一会儿。没有回复，但心里某个地方被说中了。",
      "effect": "typewriter",
      "speed": 55,
      "character_image": "assets/char_林羽_calm.png"
    },
    {
      "id": "s52",
      "text": "林羽站起身，走到窗前，望着夜空，城市的灯光把云层染成橙色，找不到一颗星星。他知道，自己还有很长的路要走，但他已经不再害怕那条路的长度了。",
      "effect": "typewriter",
      "speed": 55,
      "background": {
        "image": "assets/bg_street_night.png"
      },
      "character_image": "assets/char_林羽_calm.png"
    },
    {
      "id": "s53",
      "text": "深夜，林羽坐在电脑前，反复观看自己和李昊对战的录像。屏幕上的每一个细节都清晰可见，他把播放速度调到了0.5倍，一帧一帧地看。",
      "effect": "typewriter",
      "speed": 55,
      "background": {
        "effects": [
          "fade"
        ],
        "image": "assets/bg_room_night.png"
      },
      "character_image": "assets/char_李昊_confident.png"
    },
    {
      "id": "s54",
      "text": "\"为什么我总是在关键时刻失误？\"林羽在心里问自己。他拿了一张草稿纸，把自己频繁出错的时间节点一个个圈出来：开场被压制时、连段出完被对方看穿后……密密麻麻圈了七个。",
      "effect": "typewriter",
      "speed": 55,
      "character_image": "assets/char_林羽_calm.png"
    },
    {
      "id": "s55",
      "text": "录像中，林羽的角色在一次对攻中被对手抓住破绽，连续挨打。他仔细观察李昊的操作，发现对方总是能在最恰当的时机反击，而不是见招拆招地死扛——是在等，在引。",
      "effect": "typewriter",
      "speed": 55,
      "background": {
        "image": "assets/bg_room_night.png"
      },
      "character_image": "assets/char_李昊_confident.png"
    },
    {
      "id": "s56",
      "text": "\"原来如此。\"林羽突然明白了什么。他意识到，自己一直在追求华丽的连招，却忽视了节奏的控制——苏瑶说过这句话，当时他以为自己懂了，原来没懂。",
      "effect": "typewriter",
      "speed": 55,
      "character_image": "assets/char_苏瑶_friendly.png"
    },
    {
      "id": "s57",
      "text": "林羽开始重新审视自己的操作风格，不再追求连段的华丽，而是注重每一次出手的\"时机密度\"——快的时候快，慢的时候真的慢，用节奏变化把对手打乱。他反复练习，逐渐找到了感觉。",
      "effect": "typewriter",
      "speed": 55,
      "character_image": "assets/char_林羽_calm.png"
    },
    {
      "id": "s58",
      "text": "那是某天凌晨两点，他打开排位赛，连赢了三局，中间没有停下来欢呼，只是换了换坐姿，继续。",
      "effect": "shake",
      "speed": 15,
      "background": {
        "image": "assets/bg_room_night.png"
      },
      "character_image": "assets/char_林羽_winning.png"
    },
    {
      "id": "s59",
      "text": "第二天，他把这个心得发消息告诉了苏瑶。",
      "effect": "typewriter",
      "speed": 55,
      "background": {
        "effects": [
          "fade"
        ]
      },
      "character_image": "assets/char_苏瑶_friendly.png"
    },
    {
      "id": "s60",
      "text": "苏瑶回复得很快，只有一句话：\"对，这才是你的打法。\"",
      "effect": "typewriter",
      "speed": 55,
      "character_image": "assets/char_苏瑶_friendly.png"
    },
    {
      "id": "s61",
      "text": "林羽把手机屏幕按灭，重新握上手柄。六个字，轻描淡写，但他看了不止一次。",
      "effect": "typewriter",
      "speed": 55,
      "character_image": "assets/char_林羽_calm.png"
    },
    {
      "id": "s62",
      "text": "几天后，苏瑶约他去游戏厅打了几局。林羽的改变苏瑶看在眼里——以前他总是进攻性很强，现在变得有耐心了，守得住，等得到。",
      "effect": "typewriter",
      "speed": 55,
      "background": {
        "effects": [
          "fade"
        ],
        "image": "assets/bg_arcade_evening.png"
      },
      "character_image": "assets/char_苏瑶_friendly.png"
    },
    {
      "id": "s63",
      "text": "\"比上次稳多了。\"苏瑶把外套叠起来放在腿上，\"我说你那个冲动的毛病一直是个软肋。\"",
      "effect": "typewriter",
      "speed": 55,
      "character_image": "assets/char_苏瑶_friendly.png"
    },
    {
      "id": "s64",
      "text": "\"说得我像个暴力分子。\"林羽没好气地回。",
      "effect": "typewriter",
      "speed": 55,
      "character_image": "assets/char_林羽_calm.png"
    },
    {
      "id": "s65",
      "text": "苏瑶笑起来，声音清脆，游戏厅的噪声里也听得很清楚。",
      "effect": "typewriter",
      "speed": 55,
      "background": {
        "image": "assets/bg_arcade_evening.png"
      },
      "character_image": "assets/char_苏瑶_friendly.png"
    },
    {
      "id": "s66",
      "text": "林羽在段位赛里开始稳定上分，从黄金一路打到了铂金边缘。他没有和任何人说，只是每天打完之后在手机备忘录里记一条今天学到了什么——有时候一个字都写不出来，有时候能写一整段。",
      "effect": "typewriter",
      "speed": 55,
      "character_image": "assets/char_林羽_calm.png"
    },
    {
      "id": "s67",
      "text": "那些文字很粗糙，但全是他自己的。",
      "effect": "typewriter",
      "speed": 55,
      "character_image": "assets/char_林羽_calm.png"
    },
    {
      "id": "s68",
      "text": "有一天和对手打到了最后一局最后一血，林羽手心全是汗，他做了一个很笨但很准的防守反击，把那一局拿下来。他没有站起来，也没有叫出来，只是在房间里静静地坐着，感受那个胜利停在胸腔里的感觉。",
      "effect": "typewriter",
      "speed": 55,
      "background": {
        "image": "assets/bg_room_night.png"
      },
      "character_image": "assets/char_林羽_winning.png"
    },
    {
      "id": "s69",
      "text": "像是某趟很长的夜班车终于到站。",
      "effect": "typewriter",
      "speed": 55,
      "character_image": "assets/char_林羽_calm.png"
    },
    {
      "id": "s70",
      "text": "几周后，林羽再次站在了李昊面前——这次是在游戏厅，当面坐着的那种。两台并排的街霸6机台，李昊已经在了，正在暖手。林羽把外套搭在椅背上，坐下去，没有说话，插了币。",
      "effect": "typewriter",
      "speed": 55,
      "background": {
        "effects": [
          "fade"
        ],
        "image": "assets/bg_room_night.png"
      },
      "character_image": "assets/char_李昊_confident.png"
    },
    {
      "id": "s71",
      "text": "\"哟，又来了。\"李昊侧过头看了他一眼，语气里多了些什么，说不清。",
      "effect": "typewriter",
      "speed": 55,
      "character_image": "assets/char_李昊_confident.png"
    },
    {
      "id": "s72",
      "text": "\"嗯。\"林羽只应了一个字。",
      "effect": "typewriter",
      "speed": 55,
      "character_image": "assets/char_林羽_calm.png"
    },
    {
      "id": "s73",
      "text": "比赛开始的前几秒，游戏厅里的噪声好像突然远了。林羽把注意力全部压进屏幕里，感受那个角色的存在感——站位、距离、节奏。他不再像以前那样急着出手。",
      "effect": "typewriter",
      "speed": 55,
      "background": {
        "image": "assets/bg_arcade_evening.png"
      },
      "character_image": "assets/char_林羽_calm.png"
    },
    {
      "id": "s74",
      "text": "李昊冲上来，林羽退了一步，守住，等了一拍，然后反击。两人的角色在屏幕上交缠，第一局打得很胶着。",
      "effect": "shake",
      "speed": 15,
      "character_image": "assets/char_李昊_confident.png"
    },
    {
      "id": "s75",
      "text": "第一局，林羽输了，凭一口气没守住。",
      "effect": "typewriter",
      "speed": 55,
      "character_image": "assets/char_林羽_frustrated.png"
    },
    {
      "id": "s76",
      "text": "他深吸一口气，继续。",
      "effect": "typewriter",
      "speed": 55,
      "character_image": "assets/char_林羽_calm.png"
    },
    {
      "id": "s77",
      "text": "第二局，李昊开始施压，连段接连打进来，林羽挡了一半，另一半只能扛着。但他在扛的过程里找到了一个间隙——李昊有个习惯动作，连段的第三击之后会习惯性退步，林羽在心里记下来，等。",
      "effect": "typewriter",
      "speed": 55,
      "character_image": "assets/char_李昊_confident.png"
    },
    {
      "id": "s78",
      "text": "第二局结束，林羽赢了。旁边有人轻轻叫了一声。",
      "effect": "shake",
      "speed": 15,
      "character_image": "assets/char_林羽_winning.png"
    },
    {
      "id": "s79",
      "text": "第三局，决胜局。两人都打得很慢，慢到有点奇怪，像两个棋手在盯着棋盘算路数。游戏厅里不知道什么时候多了几个人站着看。",
      "effect": "shake",
      "speed": 15,
      "background": {
        "image": "assets/bg_arcade_evening.png"
      },
      "character_image": "assets/char_林羽_calm.png"
    },
    {
      "id": "s80",
      "text": "林羽的手心已经干了，他反而更冷静。他想起苏瑶说的那句话：找到自己的节奏。他的节奏是什么？是慢，是等，是一刀进去必须是有把握的一刀。",
      "effect": "typewriter",
      "speed": 55,
      "character_image": "assets/char_苏瑶_friendly.png"
    },
    {
      "id": "s81",
      "text": "最后三十格血，李昊攻上来，林羽横移躲开，抓住落空后的空隙，打出最后一个完整连段。李昊的角色倒下去。",
      "effect": "shake",
      "speed": 15,
      "character_image": "assets/char_李昊_confident.png"
    },
    {
      "id": "s82",
      "text": "屏幕上\"胜利\"的字出现了。",
      "effect": "typewriter",
      "speed": 55,
      "character_image": "assets/char_林羽_winning.png"
    },
    {
      "id": "s83",
      "text": "林羽没动，手放在手柄上，听见自己的心跳。",
      "effect": "typewriter",
      "speed": 55,
      "background": {
        "image": "assets/bg_room_night.png"
      },
      "character_image": "assets/char_林羽_calm.png"
    },
    {
      "id": "s84",
      "text": "李昊站起身，转过来看林羽。脸上不是那种败者的表情，更像是在打量什么。他拍了拍林羽的肩膀，\"赢得不难看。\"",
      "effect": "typewriter",
      "speed": 55,
      "character_image": "assets/char_李昊_confident.png"
    },
    {
      "id": "s85",
      "text": "林羽抬起头，\"你教了我很多。\"",
      "effect": "typewriter",
      "speed": 55,
      "character_image": "assets/char_林羽_calm.png"
    },
    {
      "id": "s86",
      "text": "\"我?\"李昊挑了挑眉，\"我骂过你。\"",
      "effect": "typewriter",
      "speed": 55,
      "character_image": "assets/char_李昊_confident.png"
    },
    {
      "id": "s87",
      "text": "\"被骂得很有收获。\"",
      "effect": "typewriter",
      "speed": 55,
      "character_image": "assets/char_林羽_calm.png"
    },
    {
      "id": "s88",
      "text": "李昊笑了，第一次笑，不是那种冷笑，是真的笑出来了，\"你这小子。\"",
      "effect": "typewriter",
      "speed": 55,
      "character_image": "assets/char_李昊_confident.png"
    },
    {
      "id": "s89",
      "text": "苏瑶在旁边站着，两手抱在胸前，看着这一幕，什么也没说，只是轻轻地叹了口气。不是失落，是那种看到结果和期待吻合时才会有的，一种安静的满意。",
      "effect": "typewriter",
      "speed": 55,
      "character_image": "assets/char_苏瑶_friendly.png"
    },
    {
      "id": "s90",
      "text": "林羽转过来看她，她朝他点了点头。",
      "effect": "typewriter",
      "speed": 55,
      "character_image": "assets/char_林羽_calm.png"
    },
    {
      "id": "s91",
      "text": "林羽走出游戏厅，外面的夜风把游戏厅里沾上的那些汗气都吹散了。街道上人不多，路灯打下来，地砖亮亮的。他没有马上回家，就站在门口站了一会儿。",
      "effect": "typewriter",
      "speed": 55,
      "background": {
        "effects": [
          "fade"
        ],
        "image": "assets/bg_street_night.png"
      },
      "character_image": "assets/char_林羽_calm.png"
    },
    {
      "id": "s92",
      "text": "今晚他赢了，但他知道那不是终点。明天开服的新赛季、下一个会在网络对战里打穿他的陌生人、那个他还没有破解的角色——路很长，打不完的。",
      "effect": "shake",
      "speed": 15,
      "background": {
        "image": "assets/bg_room_night.png"
      },
      "character_image": "assets/char_林羽_winning.png"
    },
    {
      "id": "s93",
      "text": "但那不是沉重，是某种难以言说的喜悦。像是终于找到了一件值得持续去做的事。",
      "effect": "typewriter",
      "speed": 55,
      "character_image": "assets/char_林羽_calm.png"
    },
    {
      "id": "s94",
      "text": "林羽把外套穿上，背对游戏厅走进夜色里。",
      "effect": "typewriter",
      "speed": 55,
      "background": {
        "image": "assets/bg_street_night.png"
      },
      "character_image": "assets/char_林羽_calm.png"
    },
    {
      "id": "s95",
      "text": "手机震动了一下，是苏瑶发来的消息：\"今晚回去早点睡别熬夜。\"",
      "effect": "typewriter",
      "speed": 55,
      "character_image": "assets/char_苏瑶_friendly.png"
    },
    {
      "id": "s96",
      "text": "下面跟了一句：\"也可以再打两局再睡。\"",
      "effect": "typewriter",
      "speed": 55,
      "character_image": "assets/char_林羽_calm.png"
    },
    {
      "id": "s97",
      "text": "林羽看着那两条消息，嘴角翘了起来，回了一个字：\"好。\"",
      "effect": "typewriter",
      "speed": 55,
      "character_image": "assets/char_林羽_calm.png"
    }
  ],
  "shared": {
    "planning": {
      "requirements_summary": "情绪基调是热血励志且带有日常喜剧元素。核心矛盾为主角在街霸6游戏中从菜鸟不断成长的历程。目标体验是让受众感受到主角在游戏竞技中的孤独探索、逐渐领悟自我价值的过程，像一场充满热血与欢笑的成长之旅。",
      "script_form": "visual_novel",
      "planning_source": "ai_auto",
      "reference_article": {
        "title": "银河铁道之夜",
        "usage": "theme_tone_only"
      },
      "worldview": "故事发生在现代都市，游戏厅里人群熙攘，家庭电脑成为很多玩家的选择，网络对战环境也十分流行。街霸6不仅仅是一款格斗游戏，更像是一个能让人磨炼意志、提升反应能力、探索自身潜力的特殊场所。故事主要围绕主角所在的城市展开，游戏厅是初期的重要场景，主角的房间则是他日常练习和思考的地方，网络对战则跨越了空间的限制。",
      "characters": [
        {
          "name": "林羽",
          "profile": "主角。身材瘦小但眼神坚定，留着一头黑色短发，常穿着带有街霸元素的T恤和牛仔裤。性格坚韧不拔，充满热情，有点小倔强。从小就对格斗游戏感兴趣，但一直技术平平，在生活中也比较内向。标志性台词：我一定要在街霸6里打出名堂！"
        },
        {
          "name": "苏瑶",
          "profile": "主角的朋友兼游戏导师。扎着马尾辫，眼睛明亮有神，皮肤白皙，身材娇小。性格开朗乐观，善良热心。资深游戏玩家，擅长多种格斗游戏。标志性台词：林羽，格斗游戏最重要的是找到自己的节奏哦。"
        },
        {
          "name": "李昊",
          "profile": "主角的竞争对手。高大强壮，短发显得很干练，穿着一身运动装。性格豪爽直率，有些自负。街霸6的高手，在游戏厅小有名气。标志性台词：就你这水平，还想跟我斗？"
        }
      ],
      "outline": [
        {
          "chapter": 1,
          "title": "初入街霸6的世界",
          "summary": "主角林羽第一次接触街霸6，在游戏厅被各种高手虐。情绪从期待兴奋到沮丧低落。苏瑶安慰鼓励，李昊嘲笑。段位：青铜。"
        },
        {
          "chapter": 2,
          "title": "刻苦练习",
          "summary": "林羽回家刻苦练习，网上找教程。遇到瓶颈，受网上励志故事激励重新振作。段位：白银，掌握简单连招。"
        },
        {
          "chapter": 3,
          "title": "小试牛刀",
          "summary": "林羽在游戏厅找水平相近的玩家对战，尝到胜利滋味。从紧张到兴奋，信心大增。段位：黄金。"
        },
        {
          "chapter": 4,
          "title": "遭遇强敌",
          "summary": "网络对战遭遇李昊，被打得落花流水。自信到受挫，开始反思。段位停滞黄金。"
        },
        {
          "chapter": 5,
          "title": "领悟真谛",
          "summary": "林羽结合自身特点创造独特战斗风格。苏瑶认可。从困惑到豁然开朗。段位：向铂金攀升。"
        },
        {
          "chapter": 6,
          "title": "挑战自我",
          "summary": "再次挑战李昊，激烈对战后获胜。李昊心服口服。林羽领悟格斗游戏的真正意义。段位：铂金。"
        }
      ],
      "user_keywords": null
    },
    "drafts": {
      "planning_draft_path": "scripts/励志打遍天下无敌手——我是指街霸6/drafts/planning_draft.md",
      "novel_draft_path": "scripts/励志打遍天下无敌手——我是指街霸6/drafts/novel_draft.md"
    },
    "style_contract": {
      "background_style_anchor": "anime visual novel background, clean lineart, soft global illumination, cinematic composition, modern urban gaming atmosphere",
      "background_negative_anchor": "低质量, 模糊, 水印, 文本, 人物, 人影",
      "character_style_anchor": "anime visual novel character illustration, clean lineart, cel shading, stable character design, modern casual streetwear style",
      "character_negative_anchor": "低质量, 模糊, 水印, 文本, 畸形, 多余肢体"
    },
    "character_refs": [
      {
        "name": "林羽",
        "image": "assets/char_ref_林羽_v1.png"
      },
      {
        "name": "苏瑶",
        "image": "assets/char_ref_苏瑶_v1.png"
      },
      {
        "name": "李昊",
        "image": "assets/char_ref_李昊_v1.png"
      }
    ],
    "asset_manifest": [
      {
        "segment_id": "s1",
        "background_image": "assets/bg_arcade_evening.png",
        "character_image": "assets/char_林羽_calm.png"
      },
      {
        "segment_id": "s2",
        "character_image": "assets/char_林羽_calm.png"
      },
      {
        "segment_id": "s3",
        "character_image": "assets/char_林羽_frustrated.png"
      },
      {
        "segment_id": "s4",
        "character_image": "assets/char_苏瑶_friendly.png"
      },
      {
        "segment_id": "s5",
        "character_image": "assets/char_苏瑶_friendly.png"
      },
      {
        "segment_id": "s6",
        "character_image": "assets/char_苏瑶_friendly.png"
      },
      {
        "segment_id": "s7",
        "character_image": "assets/char_李昊_confident.png"
      },
      {
        "segment_id": "s8",
        "character_image": "assets/char_苏瑶_friendly.png"
      },
      {
        "segment_id": "s9",
        "character_image": "assets/char_李昊_confident.png"
      },
      {
        "segment_id": "s10",
        "background_image": "assets/bg_street_night.png",
        "character_image": "assets/char_林羽_calm.png"
      },
      {
        "segment_id": "s11",
        "character_image": "assets/char_林羽_calm.png"
      },
      {
        "segment_id": "s12",
        "background_image": "assets/bg_room_night.png",
        "character_image": "assets/char_林羽_calm.png"
      },
      {
        "segment_id": "s13",
        "background_image": "assets/bg_room_night.png",
        "character_image": "assets/char_林羽_calm.png"
      },
      {
        "segment_id": "s14",
        "background_image": "assets/bg_room_night.png",
        "character_image": "assets/char_林羽_calm.png"
      },
      {
        "segment_id": "s15",
        "background_image": "assets/bg_room_night.png",
        "character_image": "assets/char_林羽_calm.png"
      },
      {
        "segment_id": "s16",
        "character_image": "assets/char_林羽_calm.png"
      },
      {
        "segment_id": "s17",
        "character_image": "assets/char_林羽_calm.png"
      },
      {
        "segment_id": "s18",
        "background_image": "assets/bg_room_night.png",
        "character_image": "assets/char_林羽_calm.png"
      },
      {
        "segment_id": "s19",
        "background_image": "assets/bg_room_night.png",
        "character_image": "assets/char_林羽_winning.png"
      },
      {
        "segment_id": "s20",
        "character_image": "assets/char_林羽_winning.png"
      },
      {
        "segment_id": "s21",
        "background_image": "assets/bg_room_night.png",
        "character_image": "assets/char_林羽_calm.png"
      },
      {
        "segment_id": "s22",
        "character_image": "assets/char_林羽_calm.png"
      },
      {
        "segment_id": "s23",
        "character_image": "assets/char_林羽_calm.png"
      },
      {
        "segment_id": "s24",
        "character_image": "assets/char_林羽_calm.png"
      },
      {
        "segment_id": "s25",
        "background_image": "assets/bg_room_night.png",
        "character_image": "assets/char_林羽_calm.png"
      },
      {
        "segment_id": "s26",
        "character_image": "assets/char_林羽_calm.png"
      },
      {
        "segment_id": "s27",
        "character_image": "assets/char_林羽_winning.png"
      },
      {
        "segment_id": "s28",
        "character_image": "assets/char_林羽_frustrated.png"
      },
      {
        "segment_id": "s29",
        "character_image": "assets/char_林羽_calm.png"
      },
      {
        "segment_id": "s30",
        "character_image": "assets/char_林羽_calm.png"
      },
      {
        "segment_id": "s31",
        "background_image": "assets/bg_arcade_evening.png",
        "character_image": "assets/char_林羽_calm.png"
      },
      {
        "segment_id": "s32",
        "background_image": "assets/bg_room_night.png",
        "character_image": "assets/char_林羽_calm.png"
      },
      {
        "segment_id": "s33",
        "character_image": "assets/char_苏瑶_friendly.png"
      },
      {
        "segment_id": "s34",
        "character_image": "assets/char_林羽_calm.png"
      },
      {
        "segment_id": "s35",
        "background_image": "assets/bg_room_night.png",
        "character_image": "assets/char_李昊_confident.png"
      },
      {
        "segment_id": "s36",
        "background_image": "assets/bg_room_night.png",
        "character_image": "assets/char_李昊_confident.png"
      },
      {
        "segment_id": "s37",
        "character_image": "assets/char_李昊_confident.png"
      },
      {
        "segment_id": "s38",
        "background_image": "assets/bg_arcade_evening.png",
        "character_image": "assets/char_林羽_frustrated.png"
      },
      {
        "segment_id": "s39",
        "character_image": "assets/char_李昊_confident.png"
      },
      {
        "segment_id": "s40",
        "character_image": "assets/char_林羽_calm.png"
      },
      {
        "segment_id": "s41",
        "character_image": "assets/char_李昊_confident.png"
      },
      {
        "segment_id": "s42",
        "character_image": "assets/char_林羽_calm.png"
      },
      {
        "segment_id": "s43",
        "character_image": "assets/char_李昊_confident.png"
      },
      {
        "segment_id": "s44",
        "character_image": "assets/char_林羽_calm.png"
      },
      {
        "segment_id": "s45",
        "character_image": "assets/char_李昊_confident.png"
      },
      {
        "segment_id": "s46",
        "background_image": "assets/bg_room_night.png",
        "character_image": "assets/char_李昊_confident.png"
      },
      {
        "segment_id": "s47",
        "character_image": "assets/char_林羽_calm.png"
      },
      {
        "segment_id": "s48",
        "background_image": "assets/bg_room_night.png",
        "character_image": "assets/char_林羽_calm.png"
      },
      {
        "segment_id": "s49",
        "character_image": "assets/char_林羽_frustrated.png"
      },
      {
        "segment_id": "s50",
        "character_image": "assets/char_李昊_confident.png"
      },
      {
        "segment_id": "s51",
        "character_image": "assets/char_林羽_calm.png"
      },
      {
        "segment_id": "s52",
        "background_image": "assets/bg_street_night.png",
        "character_image": "assets/char_林羽_calm.png"
      },
      {
        "segment_id": "s53",
        "background_image": "assets/bg_room_night.png",
        "character_image": "assets/char_李昊_confident.png"
      },
      {
        "segment_id": "s54",
        "character_image": "assets/char_林羽_calm.png"
      },
      {
        "segment_id": "s55",
        "background_image": "assets/bg_room_night.png",
        "character_image": "assets/char_李昊_confident.png"
      },
      {
        "segment_id": "s56",
        "character_image": "assets/char_苏瑶_friendly.png"
      },
      {
        "segment_id": "s57",
        "character_image": "assets/char_林羽_calm.png"
      },
      {
        "segment_id": "s58",
        "background_image": "assets/bg_room_night.png",
        "character_image": "assets/char_林羽_winning.png"
      },
      {
        "segment_id": "s59",
        "character_image": "assets/char_苏瑶_friendly.png"
      },
      {
        "segment_id": "s60",
        "character_image": "assets/char_苏瑶_friendly.png"
      },
      {
        "segment_id": "s61",
        "character_image": "assets/char_林羽_calm.png"
      },
      {
        "segment_id": "s62",
        "background_image": "assets/bg_arcade_evening.png",
        "character_image": "assets/char_苏瑶_friendly.png"
      },
      {
        "segment_id": "s63",
        "character_image": "assets/char_苏瑶_friendly.png"
      },
      {
        "segment_id": "s64",
        "character_image": "assets/char_林羽_calm.png"
      },
      {
        "segment_id": "s65",
        "background_image": "assets/bg_arcade_evening.png",
        "character_image": "assets/char_苏瑶_friendly.png"
      },
      {
        "segment_id": "s66",
        "character_image": "assets/char_林羽_calm.png"
      },
      {
        "segment_id": "s67",
        "character_image": "assets/char_林羽_calm.png"
      },
      {
        "segment_id": "s68",
        "background_image": "assets/bg_room_night.png",
        "character_image": "assets/char_林羽_winning.png"
      },
      {
        "segment_id": "s69",
        "character_image": "assets/char_林羽_calm.png"
      },
      {
        "segment_id": "s70",
        "background_image": "assets/bg_room_night.png",
        "character_image": "assets/char_李昊_confident.png"
      },
      {
        "segment_id": "s71",
        "character_image": "assets/char_李昊_confident.png"
      },
      {
        "segment_id": "s72",
        "character_image": "assets/char_林羽_calm.png"
      },
      {
        "segment_id": "s73",
        "background_image": "assets/bg_arcade_evening.png",
        "character_image": "assets/char_林羽_calm.png"
      },
      {
        "segment_id": "s74",
        "character_image": "assets/char_李昊_confident.png"
      },
      {
        "segment_id": "s75",
        "character_image": "assets/char_林羽_frustrated.png"
      },
      {
        "segment_id": "s76",
        "character_image": "assets/char_林羽_calm.png"
      },
      {
        "segment_id": "s77",
        "character_image": "assets/char_李昊_confident.png"
      },
      {
        "segment_id": "s78",
        "character_image": "assets/char_林羽_winning.png"
      },
      {
        "segment_id": "s79",
        "background_image": "assets/bg_arcade_evening.png",
        "character_image": "assets/char_林羽_calm.png"
      },
      {
        "segment_id": "s80",
        "character_image": "assets/char_苏瑶_friendly.png"
      },
      {
        "segment_id": "s81",
        "character_image": "assets/char_李昊_confident.png"
      },
      {
        "segment_id": "s82",
        "character_image": "assets/char_林羽_winning.png"
      },
      {
        "segment_id": "s83",
        "background_image": "assets/bg_room_night.png",
        "character_image": "assets/char_林羽_calm.png"
      },
      {
        "segment_id": "s84",
        "character_image": "assets/char_李昊_confident.png"
      },
      {
        "segment_id": "s85",
        "character_image": "assets/char_林羽_calm.png"
      },
      {
        "segment_id": "s86",
        "character_image": "assets/char_李昊_confident.png"
      },
      {
        "segment_id": "s87",
        "character_image": "assets/char_林羽_calm.png"
      },
      {
        "segment_id": "s88",
        "character_image": "assets/char_李昊_confident.png"
      },
      {
        "segment_id": "s89",
        "character_image": "assets/char_苏瑶_friendly.png"
      },
      {
        "segment_id": "s90",
        "character_image": "assets/char_林羽_calm.png"
      },
      {
        "segment_id": "s91",
        "background_image": "assets/bg_street_night.png",
        "character_image": "assets/char_林羽_calm.png"
      },
      {
        "segment_id": "s92",
        "background_image": "assets/bg_room_night.png",
        "character_image": "assets/char_林羽_winning.png"
      },
      {
        "segment_id": "s93",
        "character_image": "assets/char_林羽_calm.png"
      },
      {
        "segment_id": "s94",
        "background_image": "assets/bg_street_night.png",
        "character_image": "assets/char_林羽_calm.png"
      },
      {
        "segment_id": "s95",
        "character_image": "assets/char_苏瑶_friendly.png"
      },
      {
        "segment_id": "s96",
        "character_image": "assets/char_林羽_calm.png"
      },
      {
        "segment_id": "s97",
        "character_image": "assets/char_林羽_calm.png"
      }
    ],
    "pipeline_state": {
      "stage": "4",
      "updated_at": "2026-03-03",
      "presentation_done": true,
      "presentation_segments": 97,
      "generated_backgrounds": 3,
      "generated_character_poses": 5,
      "reused_assets": 28
    }
  }
}